Metadata-Version: 1.0
Name: mml-gmm
Version: 0.1
Summary: Unsupervised cluster selection
Home-page: https://github.com/abriosi/MML_GMM/
Author: abriosi
Author-email: UNKNOWN
License: MIT
Platform: UNKNOWN
